{
  "openapi": "3.0.0",
  "info": {
    "title": "Food",
    "version": "1.0.0"
  },
  "paths": {
    "/{id}/shawrma": {
      "put": {
        "description": "",
        "tags": [
          "Shawrma"
        ],
        "operationId": "866a11be-17a4-4204-a602-cf841ee181cb",
        "summary": "Replace Shawrma",
        "responses": {
          "200": {
            "description": "",
            "content": {
              "application/json": {
                "schema": {
                  "type": "object",
                  "properties": {
                    "data": {
                      "type": "object",
                      "properties": {}
                    }
                  }
                }
              }
            }
          },
          "400": {
            "description": "Bad Request",
            "content": {
              "application/json": {
                "schema": {
                  "$ref": "#/components/schemas/Error"
                }
              }
            }
          },
          "parameters": [
            {
              "schema": {},
              "name": "id",
              "in": "path",
              "example": ""
            }
          ]
        }
      },
      "delete": {
        "description": "",
        "tags": [
          "Shawrma"
        ],
        "operationId": "22428acb-e06a-4249-b827-d5fbdcd131dc",
        "summary": "Delete Shawrma",
        "responses": {
          "200": {
            "description": "",
            "content": {
              "application/json": {
                "schema": {
                  "type": "object",
                  "properties": {
                    "data": {
                      "type": "object",
                      "properties": {}
                    }
                  }
                }
              }
            }
          },
          "400": {
            "description": "Bad Request",
            "content": {
              "application/json": {
                "schema": {
                  "$ref": "#/components/schemas/Error"
                }
              }
            }
          },
          "parameters": [
            {
              "schema": {},
              "name": "id",
              "in": "path",
              "example": ""
            }
          ]
        }
      },
      "head": {
        "description": "",
        "tags": [
          "Shawrma"
        ],
        "operationId": "efdad139-536e-4e17-9e9e-713bfb0a397b",
        "summary": "Shawrma Exists",
        "responses": {
          "200": {
            "description": "",
            "content": {
              "application/json": {
                "schema": {
                  "type": "object",
                  "properties": {
                    "data": {
                      "type": "object",
                      "properties": {}
                    }
                  }
                }
              }
            }
          },
          "400": {
            "description": "Bad Request",
            "content": {
              "application/json": {
                "schema": {
                  "$ref": "#/components/schemas/Error"
                }
              }
            }
          },
          "parameters": [
            {
              "schema": {},
              "name": "id",
              "in": "path",
              "example": ""
            }
          ]
        }
      },
      "patch": {
        "description": "",
        "tags": [
          "Shawrma"
        ],
        "operationId": "d10fae05-7b27-4c91-9752-1a8df0e8c463",
        "summary": "Update Shawrma",
        "responses": {
          "200": {
            "description": "",
            "content": {
              "application/json": {
                "schema": {
                  "type": "object",
                  "properties": {
                    "data": {
                      "type": "object",
                      "properties": {}
                    }
                  }
                }
              }
            }
          },
          "400": {
            "description": "Bad Request",
            "content": {
              "application/json": {
                "schema": {
                  "$ref": "#/components/schemas/Error"
                }
              }
            }
          },
          "parameters": [
            {
              "schema": {},
              "name": "id",
              "in": "path",
              "example": ""
            }
          ]
        }
      },
      "get": {
        "description": "",
        "tags": [
          "Shawrma"
        ],
        "operationId": "b97e10f3-88be-4be9-8860-f104da6140c1",
        "summary": "Get Shawrma",
        "responses": {
          "200": {
            "description": "",
            "content": {
              "application/json": {
                "schema": {
                  "type": "object",
                  "properties": {
                    "data": {
                      "type": "object",
                      "properties": {}
                    }
                  }
                }
              }
            }
          },
          "400": {
            "description": "Bad Request",
            "content": {
              "application/json": {
                "schema": {
                  "$ref": "#/components/schemas/Error"
                }
              }
            }
          },
          "parameters": [
            {
              "schema": {},
              "name": "id",
              "in": "path",
              "example": ""
            }
          ]
        }
      }
    },
    "/shawrma": {
      "post": {
        "description": "",
        "tags": [
          "Shawrma"
        ],
        "operationId": "e29dba1f-977d-4a69-97b3-b1ccefd74765",
        "summary": "Create Shawrma",
        "requestBody": {
          "required": true,
          "content": {
            "application/json": {
              "schema": {
                "description": "",
                "type": "object",
                "properties": {
                  "kind": {
                    "required": true,
                    "minLength": 1,
                    "type": "string"
                  }
                },
                "required": [
                  "kind"
                ]
              }
            }
          }
        },
        "responses": {
          "200": {
            "description": "",
            "content": {
              "application/json": {
                "schema": {
                  "type": "object",
                  "properties": {
                    "data": {
                      "type": "object",
                      "properties": {
                        "id": {
                          "type": "string"
                        }
                      }
                    }
                  }
                }
              }
            }
          },
          "400": {
            "description": "Bad Request",
            "content": {
              "application/json": {
                "schema": {
                  "$ref": "#/components/schemas/Error"
                }
              }
            }
          },
          "parameters": []
        }
      },
      "get": {
        "description": "",
        "tags": [
          "Shawrma"
        ],
        "operationId": "5ae59395-779d-4380-a79e-870fbe0cb8a2",
        "summary": "List Shawrmas",
        "responses": {
          "200": {
            "description": "",
            "content": {
              "application/json": {
                "schema": {
                  "type": "object",
                  "properties": {
                    "data": {
                      "type": "object",
                      "properties": {
                        "data": {
                          "type": "{ id: string; deletedAt: Date; createdAt: Date; updatedAt: Date; kind: string; }[]"
                        },
                        "meta": {
                          "type": "{ hasNextPage: boolean; hasPreviousPage: boolean; pageSize: number; currentPage: number; totalCount: number; totalPages: number; }"
                        }
                      }
                    }
                  }
                }
              }
            }
          },
          "400": {
            "description": "Bad Request",
            "content": {
              "application/json": {
                "schema": {
                  "$ref": "#/components/schemas/Error"
                }
              }
            }
          },
          "parameters": [
            {
              "schema": {
                "type": "number",
                "minimum": 1
              },
              "name": "pageSize",
              "in": "query",
              "example": ""
            },
            {
              "schema": {
                "type": "number",
                "minimum": 1
              },
              "name": "pageNo",
              "in": "query",
              "example": ""
            }
          ]
        }
      }
    }
  },
  "components": {
    "schemas": {
      "Error": {
        "type": "object",
        "properties": {
          "type": {
            "type": "string",
            "description": "A URI reference [RFC3986] that identifies the problem type."
          },
          "title": {
            "type": "string",
            "description": "A short, human-readable summary of the problem type."
          },
          "status": {
            "type": "integer",
            "description": "The HTTP status code ([RFC7231], Section 6) generated by the origin server for this occurrence of the problem."
          },
          "detail": {
            "type": "string",
            "description": "A human-readable explanation specific to this occurrence of the problem."
          },
          "instance": {
            "type": "string",
            "description": "A URI reference that identifies the specific occurrence of the problem."
          },
          "errors": {
            "type": "object",
            "description": "Validation errors",
            "properties": {}
          }
        }
      }
    }
  }
}
